{
    "paths": {
        "/documents/{document_id}": {
            "get": {
                "operationId": "getDocument",
                "tags": [
                    "Documentos"
                ],
                "summary": "Obtener documento específico",
                "description": "Obtiene toda la información completa de un documento tributario específico, incluyendo el PDF y XML cuando están disponibles. El PDF siempre se incluye en la respuesta (campo `pdf_url`). Este endpoint es útil para consultar detalles completos de un documento ya emitido o recibido.\n\n**Seguridad:** El usuario solo puede acceder al documento si es emisor (sender) o receptor (receiver) del documento. Si el usuario no tiene acceso, se retorna un error 403 Forbidden.",
                "parameters": [
                    {
                        "name": "document_id",
                        "in": "path",
                        "description": "ID único del documento a consultar (entero)",
                        "required": true,
                        "schema": {
                            "type": "integer"
                        }
                    }
                ],
                "responses": {
                    "200": {
                        "description": "Documento obtenido exitosamente con PDF y XML cuando están disponibles",
                        "content": {
                            "application/json": {
                                "schema": {
                                    "$ref": "#/components/schemas/DocumentDetailWithFiles"
                                }
                            }
                        }
                    },
                    "400": {
                        "description": "Parámetros inválidos",
                        "content": {
                            "application/json": {
                                "schema": {
                                    "$ref": "#/components/schemas/Error"
                                }
                            }
                        }
                    },
                    "401": {
                        "description": "API Key faltante o inválida",
                        "content": {
                            "application/json": {
                                "schema": {
                                    "$ref": "#/components/schemas/Error"
                                }
                            }
                        }
                    },
                    "403": {
                        "description": "Sin permisos para acceder al documento. El usuario debe ser emisor (sender) o receptor (receiver) del documento.",
                        "content": {
                            "application/json": {
                                "schema": {
                                    "type": "object",
                                    "properties": {
                                        "error": {
                                            "type": "string",
                                            "example": "No tienes acceso a este documento"
                                        }
                                    }
                                }
                            }
                        }
                    },
                    "404": {
                        "description": "Documento o entidad no encontrada",
                        "content": {
                            "application/json": {
                                "schema": {
                                    "$ref": "#/components/schemas/Error"
                                }
                            }
                        }
                    }
                },
                "security": [
                    {
                        "apiKeyAuth": []
                    }
                ]
            }
        }
    }
}
